<annotation><filename>color_2015-01-16_10-49.jpg</filename><folder>users/AlexAbram//colored_sodankyla_ionograms</folder><source><submittedBy>Alexey</submittedBy></source><imagesize><nrows>240</nrows><ncols>329</ncols></imagesize><object><name>f-layer</name><deleted>0</deleted><verified>0</verified><occluded>no</occluded><attributes></attributes><parts><hasparts></hasparts><ispartof></ispartof></parts><date>13-Feb-2018 19:21:54</date><id>0</id><polygon><username>AlexAbram</username><pt><x>44</x><y>153</y></pt><pt><x>50</x><y>163</y></pt><pt><x>61</x><y>167</y></pt><pt><x>73</x><y>169</y></pt><pt><x>92</x><y>165</y></pt><pt><x>113</x><y>162</y></pt><pt><x>132</x><y>158</y></pt><pt><x>141</x><y>156</y></pt><pt><x>153</x><y>155</y></pt><pt><x>168</x><y>152</y></pt><pt><x>185</x><y>146</y></pt><pt><x>194</x><y>135</y></pt><pt><x>191</x><y>134</y></pt><pt><x>179</x><y>142</y></pt><pt><x>169</x><y>146</y></pt><pt><x>173</x><y>136</y></pt><pt><x>181</x><y>130</y></pt><pt><x>182</x><y>118</y></pt><pt><x>181</x><y>108</y></pt><pt><x>176</x><y>98</y></pt><pt><x>174</x><y>85</y></pt><pt><x>173</x><y>59</y></pt><pt><x>171</x><y>71</y></pt><pt><x>169</x><y>79</y></pt><pt><x>158</x><y>85</y></pt><pt><x>155</x><y>94</y></pt><pt><x>152</x><y>122</y></pt><pt><x>150</x><y>123</y></pt><pt><x>144</x><y>132</y></pt><pt><x>132</x><y>139</y></pt><pt><x>101</x><y>147</y></pt><pt><x>82</x><y>149</y></pt><pt><x>60</x><y>152</y></pt><pt><x>54</x><y>150</y></pt><pt><x>50</x><y>150</y></pt></polygon></object></annotation>